setup.py
nlp_services/__init__.py
nlp_services.egg-info/PKG-INFO
nlp_services.egg-info/SOURCES.txt
nlp_services.egg-info/dependency_links.txt
nlp_services.egg-info/requires.txt
nlp_services.egg-info/top_level.txt
nlp_services/api/__init__.py
nlp_services/api/app.py
nlp_services/authority/__init__.py
nlp_services/caching/__init__.py
nlp_services/discourse/__init__.py
nlp_services/discourse/entities.py
nlp_services/discourse/sentiment.py
nlp_services/document_access/__init__.py
nlp_services/pooling/__init__.py
nlp_services/scripts/__init__.py
nlp_services/scripts/distributed_entities.py
nlp_services/scripts/refresh_titles.py
nlp_services/syntax/__init__.py
nlp_services/test/__init__.py
nlp_services/test/test_document_access.py
nlp_services/title_confirmation/__init__.py
nlp_services/title_confirmation/wikia.py
nlp_services/title_confirmation/wikipedia.py
nlp_services/wikia_utils/__init__.py