Metadata-Version: 1.0
Name: nlp-services
Version: 0.0.1
Summary: A collection of services for interacting with NLP data extracted from Stanford CoreNLP
Home-page: https://github.com/relwell/nlp_services
Author: Robert Elwell
Author-email: robert.elwell@gmail.com
License: Other
Platform: UNKNOWN
